btimer/__init__.py
btimer/btimer.py
btimer/verses.json
btimer-1.0.11.dist-info/LICENSE.txt
btimer-1.0.11.dist-info/METADATA
btimer-1.0.11.dist-info/WHEEL
btimer-1.0.11.dist-info/entry_points.txt
btimer-1.0.11.dist-info/top_level.txt
btimer-1.0.11.dist-info/RECORD
