Metadata-Version: 2.1
Name: btimer
Version: 1.0.11
Summary: Help people get away from the computer
Author-email: Dylan Ngo <it.tinhngo@gmail.com>
Project-URL: Homepage, https://github.com/dylanngo95/timer
Project-URL: Bug Tracker, https://github.com/dylanngo95/timer/issues
Classifier: Programming Language :: Python :: 3
Classifier: License :: OSI Approved :: MIT License
Classifier: Operating System :: OS Independent
Requires-Python: >=3.9
License-File: LICENSE.txt
Requires-Dist: rich (==13.4.2)
